vanilla_roll/__init__.py
vanilla_roll/anatomy_orientation.py
vanilla_roll/array_api/__init__.py
vanilla_roll/array_api/cupy.py
vanilla_roll/array_api/numpy.py
vanilla_roll/array_api/pytorch.py
vanilla_roll/array_api_extra/__init__.py
vanilla_roll/array_api_extra/cupy.py
vanilla_roll/array_api_extra/numpy.py
vanilla_roll/array_api_extra/pytorch.py
vanilla_roll/array_api_extra/type.py
vanilla_roll/array_api_image/__init__.py
vanilla_roll/backend.py
vanilla_roll/camera.py
vanilla_roll/camera_sequence.py
vanilla_roll/geometry/conversion.py
vanilla_roll/geometry/element.py
vanilla_roll/geometry/linalg.py
vanilla_roll/io/__init__.py
vanilla_roll/io/dicom.py
vanilla_roll/io/mha.py
vanilla_roll/io/nifti.py
vanilla_roll/py.typed
vanilla_roll/rendering/__init__.py
vanilla_roll/rendering/algorithm.py
vanilla_roll/rendering/composition.py
vanilla_roll/rendering/image_proc.py
vanilla_roll/rendering/mode.py
vanilla_roll/rendering/orthogonal_sampling.py
vanilla_roll/rendering/orthogonal_shear_warp.py
vanilla_roll/rendering/projection.py
vanilla_roll/rendering/rendering.py
vanilla_roll/rendering/transfer_function.py
vanilla_roll/rendering/types.py
vanilla_roll/usecase.py
vanilla_roll/util.py
vanilla_roll/validation.py
vanilla_roll/volume.py
vanilla_roll-0.3.0.dist-info/LICENSE
vanilla_roll-0.3.0.dist-info/WHEEL
vanilla_roll-0.3.0.dist-info/METADATA
vanilla_roll-0.3.0.dist-info/RECORD
