Metadata-Version: 2.1
Name: vanilla-roll
Version: 0.3.0
Summary: A simple array based volume renderer
Home-page: https://github.com/ar90n/vanilla_roll
License: Apache-2.0
Keywords: array-api,volume rendering
Author: Masahiro Wada
Author-email: argon.argon.argon@gmail.com
Requires-Python: >=3.10,<3.11
Classifier: License :: OSI Approved :: Apache Software License
Classifier: Programming Language :: Python :: 3
Classifier: Programming Language :: Python :: 3.10
Provides-Extra: cupy
Provides-Extra: dicom
Provides-Extra: mha
Provides-Extra: nifti
Provides-Extra: torch
Requires-Dist: cupy (>=11.2.0,<12.0.0); extra == "cupy"
Requires-Dist: metaimageio (>=1.0.0,<2.0.0); extra == "mha"
Requires-Dist: nibabel (>=4.0.0,<5.0.0); extra == "nifti"
Requires-Dist: numpy (>=1.23.0,<2.0.0)
Requires-Dist: pydicom (>=2.3.0,<3.0.0); extra == "dicom"
Requires-Dist: torch (>=1.8.0,<2.0.0); extra == "torch"
Project-URL: Repository, https://github.com/ar90n/vanilla_roll
